fluvii/__init__.py
fluvii/config_bases.py
fluvii/exceptions.py
fluvii/general_utils.py
fluvii/logging_utils.py
fluvii/apps/__init__.py
fluvii/apps/config.py
fluvii/apps/fluvii_app.py
fluvii/apps/fluvii_multi_msg_app.py
fluvii/apps/fluvii_table_app.py
fluvii/apps/helpers/__init__.py
fluvii/apps/helpers/app_factory_base.py
fluvii/apps/helpers/rebalance_manager.py
fluvii/apps/transactions/__init__.py
fluvii/apps/transactions/consumer.py
fluvii/apps/transactions/producer.py
fluvii/apps/transactions/transaction.py
fluvii/cli/__init__.py
fluvii/cli/__main__.py
fluvii/cli/commands/__init__.py
fluvii/cli/commands/base.py
fluvii/cli/commands/topics.py
fluvii/components/__init__.py
fluvii/components/admin/__init__.py
fluvii/components/admin/admin.py
fluvii/components/admin/config.py
fluvii/components/auth/__init__.py
fluvii/components/auth/config.py
fluvii/components/consumer/__init__.py
fluvii/components/consumer/config.py
fluvii/components/consumer/consumer.py
fluvii/components/consumer/consumer_factory.py
fluvii/components/metrics/__init__.py
fluvii/components/metrics/manager/__init__.py
fluvii/components/metrics/manager/config.py
fluvii/components/metrics/manager/metrics_manager.py
fluvii/components/metrics/pusher/__init__.py
fluvii/components/metrics/pusher/config.py
fluvii/components/metrics/pusher/metrics_pusher.py
fluvii/components/producer/__init__.py
fluvii/components/producer/config.py
fluvii/components/producer/producer.py
fluvii/components/producer/producer_factory.py
fluvii/components/schema_registry/__init__.py
fluvii/components/schema_registry/config.py
fluvii/components/schema_registry/schema_registry.py
fluvii/components/sqlite/__init__.py
fluvii/components/sqlite/config.py
fluvii/components/sqlite/sqlite.py
fluvii/kafka_tools/__init__.py
fluvii/kafka_tools/fluvii_toolbox.py
fluvii/kafka_tools/topic_dumper.py
tests/__init__.py
tests/temp_integration/__init__.py
tests/temp_integration/integration.py
tests/unit/__init__.py
tests/unit/test_consumer.py
fluvii-1.1.1.dist-info/LICENSE
fluvii-1.1.1.dist-info/METADATA
fluvii-1.1.1.dist-info/WHEEL
fluvii-1.1.1.dist-info/entry_points.txt
fluvii-1.1.1.dist-info/top_level.txt
fluvii-1.1.1.dist-info/RECORD
